Metadata-Version: 1.1
Name: genecoder
Version: 1.1.1
Summary: code analysis for genes
Home-page: https://github.com/kerug/genecoder
Author: kerug
Author-email: keru.work@gmail.com
License: MIT
Keywords: analyze gene
Platform: UNKNOWN
Classifier: Topic :: Scientific/Engineering :: Bio-Informatics
